invenio_migrator/__init__.py
invenio_migrator/cli.py
invenio_migrator/ext.py
invenio_migrator/proxies.py
invenio_migrator/records.py
invenio_migrator/utils.py
invenio_migrator/version.py
invenio_migrator/legacy/__init__.py
invenio_migrator/legacy/access.py
invenio_migrator/legacy/bibdocfile.py
invenio_migrator/legacy/cli.py
invenio_migrator/legacy/clients.py
invenio_migrator/legacy/communities.py
invenio_migrator/legacy/deposit.py
invenio_migrator/legacy/featured_communities.py
invenio_migrator/legacy/records.py
invenio_migrator/legacy/remoteaccounts.py
invenio_migrator/legacy/remotetokens.py
invenio_migrator/legacy/tokens.py
invenio_migrator/legacy/userexts.py
invenio_migrator/legacy/users.py
invenio_migrator/legacy/utils.py
invenio_migrator/tasks/__init__.py
invenio_migrator/tasks/communities.py
invenio_migrator/tasks/deposit.py
invenio_migrator/tasks/errors.py
invenio_migrator/tasks/oauth2server.py
invenio_migrator/tasks/oauthclient.py
invenio_migrator/tasks/records.py
invenio_migrator/tasks/users.py
invenio_migrator/tasks/utils.py
invenio_migrator-1.0.0a10.dist-info/AUTHORS.rst
invenio_migrator-1.0.0a10.dist-info/LICENSE
invenio_migrator-1.0.0a10.dist-info/METADATA
invenio_migrator-1.0.0a10.dist-info/WHEEL
invenio_migrator-1.0.0a10.dist-info/entry_points.txt
invenio_migrator-1.0.0a10.dist-info/top_level.txt
invenio_migrator-1.0.0a10.dist-info/RECORD
