Metadata-Version: 2.1
Name: invenio-migrator
Version: 1.0.0a10
Summary: Utilities for migrating past Invenio versions to Invenio 3.0.
Home-page: https://github.com/inveniosoftware/invenio-migrator
Author: CERN
Author-email: info@inveniosoftware.org
License: GPLv2
Keywords: invenio migration
Platform: any
Classifier: Environment :: Web Environment
Classifier: Intended Audience :: Developers
Classifier: License :: OSI Approved :: GNU General Public License v2 (GPLv2)
Classifier: Operating System :: OS Independent
Classifier: Programming Language :: Python
Classifier: Topic :: Internet :: WWW/HTTP :: Dynamic Content
Classifier: Topic :: Software Development :: Libraries :: Python Modules
Classifier: Programming Language :: Python :: 2
Classifier: Programming Language :: Python :: 2.7
Classifier: Programming Language :: Python :: 3
Classifier: Programming Language :: Python :: 3.5
Classifier: Programming Language :: Python :: Implementation :: CPython
Classifier: Development Status :: 3 - Alpha
Requires-Dist: Click (>=6.3)
Requires-Dist: six (>=1.10.0)
Requires-Dist: Werkzeug (>=0.14)
Provides-Extra: all
Requires-Dist: invenio-oauth2server (>=1.0.3) ; extra == 'all'
Requires-Dist: invenio-oauthclient (>=1.0.0a7) ; extra == 'all'
Requires-Dist: check-manifest (>=0.25) ; extra == 'all'
Requires-Dist: coverage (>=4.0) ; extra == 'all'
Requires-Dist: isort (>=4.2.2) ; extra == 'all'
Requires-Dist: pydocstyle (>=1.0.0) ; extra == 'all'
Requires-Dist: pytest-cache (>=1.0) ; extra == 'all'
Requires-Dist: pytest-cov (>=2.6.0) ; extra == 'all'
Requires-Dist: pytest-pep8 (>=1.0.6) ; extra == 'all'
Requires-Dist: pytest (>=3.6) ; extra == 'all'
Requires-Dist: invenio-userprofiles (>=1.0.0a8) ; extra == 'all'
Requires-Dist: invenio-deposit (>=1.0.0a6) ; extra == 'all'
Requires-Dist: invenio-communities (>=1.0.0a13) ; extra == 'all'
Requires-Dist: Sphinx (<1.6,>=1.4.2) ; extra == 'all'
Requires-Dist: oauthlib (<3.0.0,>=1.1.2) ; extra == 'all'
Requires-Dist: requests-oauthlib (<1.2.0,>=0.5.0) ; extra == 'all'
Requires-Dist: Flask-OAuthlib (>=0.9.3) ; extra == 'all'
Requires-Dist: Flask-CeleryExt (>=0.2.0) ; extra == 'all'
Requires-Dist: Flask (>=0.11.1) ; extra == 'all'
Requires-Dist: arrow (>=0.7.0) ; extra == 'all'
Requires-Dist: dojson (>=1.0.0) ; extra == 'all'
Requires-Dist: invenio-db[versioning] (>=1.0.0b3) ; extra == 'all'
Requires-Dist: invenio-files-rest (>=1.0.0a13) ; extra == 'all'
Requires-Dist: invenio-pidstore (>=1.0.0b1) ; extra == 'all'
Requires-Dist: invenio-records (>=1.0.0b1) ; extra == 'all'
Requires-Dist: invenio-records-files (>=1.0.0a7) ; extra == 'all'
Requires-Dist: invenio-sipstore (==1.0.0a3) ; extra == 'all'
Requires-Dist: elasticsearch (<3.0.0,>=2.0.0) ; extra == 'all'
Requires-Dist: elasticsearch-dsl (<3.0.0,>=2.0.0) ; extra == 'all'
Requires-Dist: celery (<4.0,>=3.1) ; extra == 'all'
Requires-Dist: SQLAlchemy-Continuum (<1.3.5,>=1.3) ; extra == 'all'
Requires-Dist: urllib3 (<1.25,>=1.21.1) ; extra == 'all'
Requires-Dist: idna (<2.8,>=2.5) ; extra == 'all'
Provides-Extra: communities
Requires-Dist: invenio-communities (>=1.0.0a13) ; extra == 'communities'
Provides-Extra: deposit
Requires-Dist: invenio-deposit (>=1.0.0a6) ; extra == 'deposit'
Provides-Extra: docs
Requires-Dist: Sphinx (<1.6,>=1.4.2) ; extra == 'docs'
Provides-Extra: loader
Requires-Dist: oauthlib (<3.0.0,>=1.1.2) ; extra == 'loader'
Requires-Dist: requests-oauthlib (<1.2.0,>=0.5.0) ; extra == 'loader'
Requires-Dist: Flask-OAuthlib (>=0.9.3) ; extra == 'loader'
Requires-Dist: Flask-CeleryExt (>=0.2.0) ; extra == 'loader'
Requires-Dist: Flask (>=0.11.1) ; extra == 'loader'
Requires-Dist: arrow (>=0.7.0) ; extra == 'loader'
Requires-Dist: dojson (>=1.0.0) ; extra == 'loader'
Requires-Dist: invenio-db[versioning] (>=1.0.0b3) ; extra == 'loader'
Requires-Dist: invenio-files-rest (>=1.0.0a13) ; extra == 'loader'
Requires-Dist: invenio-pidstore (>=1.0.0b1) ; extra == 'loader'
Requires-Dist: invenio-records (>=1.0.0b1) ; extra == 'loader'
Requires-Dist: invenio-records-files (>=1.0.0a7) ; extra == 'loader'
Requires-Dist: invenio-sipstore (==1.0.0a3) ; extra == 'loader'
Requires-Dist: elasticsearch (<3.0.0,>=2.0.0) ; extra == 'loader'
Requires-Dist: elasticsearch-dsl (<3.0.0,>=2.0.0) ; extra == 'loader'
Requires-Dist: celery (<4.0,>=3.1) ; extra == 'loader'
Requires-Dist: SQLAlchemy-Continuum (<1.3.5,>=1.3) ; extra == 'loader'
Requires-Dist: urllib3 (<1.25,>=1.21.1) ; extra == 'loader'
Requires-Dist: idna (<2.8,>=2.5) ; extra == 'loader'
Provides-Extra: oauth2server
Requires-Dist: invenio-oauth2server (>=1.0.3) ; extra == 'oauth2server'
Provides-Extra: oauthclient
Requires-Dist: invenio-oauthclient (>=1.0.0a7) ; extra == 'oauthclient'
Provides-Extra: tests
Requires-Dist: check-manifest (>=0.25) ; extra == 'tests'
Requires-Dist: coverage (>=4.0) ; extra == 'tests'
Requires-Dist: isort (>=4.2.2) ; extra == 'tests'
Requires-Dist: pydocstyle (>=1.0.0) ; extra == 'tests'
Requires-Dist: pytest-cache (>=1.0) ; extra == 'tests'
Requires-Dist: pytest-cov (>=2.6.0) ; extra == 'tests'
Requires-Dist: pytest-pep8 (>=1.0.6) ; extra == 'tests'
Requires-Dist: pytest (>=3.6) ; extra == 'tests'
Provides-Extra: userprofiles
Requires-Dist: invenio-userprofiles (>=1.0.0a8) ; extra == 'userprofiles'
